firenze/__init__.py
firenze/cli.py
firenze/exceptions.py
firenze/notebook.py
firenze/progress.py
firenze-0.1.4.dist-info/LICENSE.md
firenze-0.1.4.dist-info/METADATA
firenze-0.1.4.dist-info/WHEEL
firenze-0.1.4.dist-info/entry_points.txt
firenze-0.1.4.dist-info/RECORD
