Metadata-Version: 2.1
Name: firenze
Version: 0.1.4
Summary: A lean executor for jupyter notebooks.
Home-page: https://github.com/pabloalcain/firenze
License: MIT
Keywords: jupyter,notebook
Author: Pablo Alcain
Author-email: pabloalcain@gmail.com
Requires-Python: >=3.9,<4.0
Classifier: License :: OSI Approved :: MIT License
Classifier: Programming Language :: Python :: 3
Classifier: Programming Language :: Python :: 3.9
Classifier: Programming Language :: Python :: 3.10
Classifier: Programming Language :: Python :: 3.11
Requires-Dist: boto3 (>=1.26.156,<2.0.0)
Requires-Dist: click (>=8.1.3,<9.0.0)
Requires-Dist: ipykernel (>=6.22.0,<7.0.0)
Requires-Dist: nbclient (>=0.7.4,<0.8.0)
Requires-Dist: nbconvert (>=7.3.1,<8.0.0)
Requires-Dist: nbformat (>=5.8.0,<6.0.0)
Project-URL: Repository, https://github.com/pabloalcain/firenze
